{
  "manifestVersion": "3.2",
  "admin": {
    "address": "0xbe70195e7e39547DC7deC6b7Ac9f55cED038d054",
    "txHash": "0xd36f39f2a45a0c1b1642c10972be4148f1fad244820ecffce138d6c129717778"
  },
  "proxies": [
    {
      "address": "0xcC5432B00F72a30849E11D2028e6F37C0A25a9ce",
      "txHash": "0xaff9619a17f7fd2427cd798d4b3fae5e6111672dc6ddf1e3d278df8dc6e6d9e3",
      "kind": "transparent"
    },
    {
      "address": "0x2e1F98E0c7EdF00580e953Ed6A58310CDb711Da1",
      "txHash": "0x9a70d7a1af254313b93719d7166ef2d040ee92bbcbc0024acba7e3c1954c40f3",
      "kind": "transparent"
    },
    {
      "address": "0x61F0273Bc171EAB86cC38D08B447664040CEAf42",
      "txHash": "0x53f3982c5c003e9324b1c91f372985db6854e9fa37fda02eafd8e92ed853ab6c",
      "kind": "transparent"
    },
    {
      "address": "0xB763AF3e507C42491BFC4834DC6F1FC02895F351",
      "txHash": "0x823b2a79a1787a7cd713cb4a6fbdee3ee53115c13b739e6f18927b7eb9d63465",
      "kind": "transparent"
    },
    {
      "address": "0x92b5A5860b005b9FecAB361d2732032b586186f7",
      "txHash": "0x7241c666719cd13701de48d8cf4ca1ba4098d241aa6fb48304e44598cd06bc5d",
      "kind": "transparent"
    }
  ],
  "impls": {
    "59ffec86a18315f6f68ec7c29d4a49703afbcf6c50ec672b0dcff06adfdfb170": {
      "address": "0xb725d55Ed3FB107e277101e38481081054761a7b",
      "txHash": "0x8da3a14543f18a031a082e2c8bc6824f9e26b7e20ab80f5df09d7d5bdc621f47",
      "layout": {
        "solcVersion": "0.8.19",
        "storage": [
          {
            "label": "_initialized",
            "offset": 0,
            "slot": "0",
            "type": "t_uint8",
            "contract": "Initializable",
            "src": "@openzeppelin/contracts-upgradeable/proxy/utils/Initializable.sol:63",
            "retypedFrom": "bool"
          },
          {
            "label": "_initializing",
            "offset": 1,
            "slot": "0",
            "type": "t_bool",
            "contract": "Initializable",
            "src": "@openzeppelin/contracts-upgradeable/proxy/utils/Initializable.sol:68"
          },
          {
            "label": "__gap",
            "offset": 0,
            "slot": "1",
            "type": "t_array(t_uint256)50_storage",
            "contract": "ContextUpgradeable",
            "src": "@openzeppelin/contracts-upgradeable/utils/ContextUpgradeable.sol:36"
          },
          {
            "label": "_owner",
            "offset": 0,
            "slot": "51",
            "type": "t_address",
            "contract": "OwnableUpgradeable",
            "src": "@openzeppelin/contracts-upgradeable/access/OwnableUpgradeable.sol:22"
          },
          {
            "label": "__gap",
            "offset": 0,
            "slot": "52",
            "type": "t_array(t_uint256)49_storage",
            "contract": "OwnableUpgradeable",
            "src": "@openzeppelin/contracts-upgradeable/access/OwnableUpgradeable.sol:94"
          },
          {
            "label": "_balances",
            "offset": 0,
            "slot": "101",
            "type": "t_mapping(t_address,t_uint256)",
            "contract": "ERC20Upgradeable",
            "src": "@openzeppelin/contracts-upgradeable/token/ERC20/ERC20Upgradeable.sol:40"
          },
          {
            "label": "_allowances",
            "offset": 0,
            "slot": "102",
            "type": "t_mapping(t_address,t_mapping(t_address,t_uint256))",
            "contract": "ERC20Upgradeable",
            "src": "@openzeppelin/contracts-upgradeable/token/ERC20/ERC20Upgradeable.sol:42"
          },
          {
            "label": "_totalSupply",
            "offset": 0,
            "slot": "103",
            "type": "t_uint256",
            "contract": "ERC20Upgradeable",
            "src": "@openzeppelin/contracts-upgradeable/token/ERC20/ERC20Upgradeable.sol:44"
          },
          {
            "label": "_name",
            "offset": 0,
            "slot": "104",
            "type": "t_string_storage",
            "contract": "ERC20Upgradeable",
            "src": "@openzeppelin/contracts-upgradeable/token/ERC20/ERC20Upgradeable.sol:46"
          },
          {
            "label": "_symbol",
            "offset": 0,
            "slot": "105",
            "type": "t_string_storage",
            "contract": "ERC20Upgradeable",
            "src": "@openzeppelin/contracts-upgradeable/token/ERC20/ERC20Upgradeable.sol:47"
          },
          {
            "label": "__gap",
            "offset": 0,
            "slot": "106",
            "type": "t_array(t_uint256)45_storage",
            "contract": "ERC20Upgradeable",
            "src": "@openzeppelin/contracts-upgradeable/token/ERC20/ERC20Upgradeable.sol:376"
          },
          {
            "label": "_paused",
            "offset": 0,
            "slot": "151",
            "type": "t_bool",
            "contract": "PausableUpgradeable",
            "src": "@openzeppelin/contracts-upgradeable/security/PausableUpgradeable.sol:29"
          },
          {
            "label": "__gap",
            "offset": 0,
            "slot": "152",
            "type": "t_array(t_uint256)49_storage",
            "contract": "PausableUpgradeable",
            "src": "@openzeppelin/contracts-upgradeable/security/PausableUpgradeable.sol:116"
          },
          {
            "label": "_accountBalanceSnapshots",
            "offset": 0,
            "slot": "201",
            "type": "t_mapping(t_address,t_struct(Snapshots)3043_storage)",
            "contract": "ERC20Snapshot",
            "src": "contracts/ERC20Snapshot.sol:61"
          },
          {
            "label": "_totalSupplySnapshots",
            "offset": 0,
            "slot": "202",
            "type": "t_struct(Snapshots)3043_storage",
            "contract": "ERC20Snapshot",
            "src": "contracts/ERC20Snapshot.sol:62"
          },
          {
            "label": "_currentSnapshotId",
            "offset": 0,
            "slot": "204",
            "type": "t_uint256",
            "contract": "ERC20Snapshot",
            "src": "contracts/ERC20Snapshot.sol:65"
          },
          {
            "label": "supplyController",
            "offset": 0,
            "slot": "205",
            "type": "t_address",
            "contract": "GIFT",
            "src": "contracts/token/GIFT.sol:21"
          },
          {
            "label": "beneficiary",
            "offset": 0,
            "slot": "206",
            "type": "t_address",
            "contract": "GIFT",
            "src": "contracts/token/GIFT.sol:22"
          },
          {
            "label": "_isExcludedFromFees",
            "offset": 0,
            "slot": "207",
            "type": "t_mapping(t_address,t_bool)",
            "contract": "GIFT",
            "src": "contracts/token/GIFT.sol:24"
          },
          {
            "label": "_isLiquidityPool",
            "offset": 0,
            "slot": "208",
            "type": "t_mapping(t_address,t_bool)",
            "contract": "GIFT",
            "src": "contracts/token/GIFT.sol:25"
          },
          {
            "label": "tierOneTaxPercentage",
            "offset": 0,
            "slot": "209",
            "type": "t_uint256",
            "contract": "GIFT",
            "src": "contracts/token/GIFT.sol:27"
          },
          {
            "label": "tierTwoTaxPercentage",
            "offset": 0,
            "slot": "210",
            "type": "t_uint256",
            "contract": "GIFT",
            "src": "contracts/token/GIFT.sol:28"
          },
          {
            "label": "tierThreeTaxPercentage",
            "offset": 0,
            "slot": "211",
            "type": "t_uint256",
            "contract": "GIFT",
            "src": "contracts/token/GIFT.sol:29"
          },
          {
            "label": "tierFourTaxPercentage",
            "offset": 0,
            "slot": "212",
            "type": "t_uint256",
            "contract": "GIFT",
            "src": "contracts/token/GIFT.sol:30"
          },
          {
            "label": "tierFiveTaxPercentage",
            "offset": 0,
            "slot": "213",
            "type": "t_uint256",
            "contract": "GIFT",
            "src": "contracts/token/GIFT.sol:31"
          },
          {
            "label": "tierOneMax",
            "offset": 0,
            "slot": "214",
            "type": "t_uint256",
            "contract": "GIFT",
            "src": "contracts/token/GIFT.sol:33"
          },
          {
            "label": "tierTwoMax",
            "offset": 0,
            "slot": "215",
            "type": "t_uint256",
            "contract": "GIFT",
            "src": "contracts/token/GIFT.sol:34"
          },
          {
            "label": "tierThreeMax",
            "offset": 0,
            "slot": "216",
            "type": "t_uint256",
            "contract": "GIFT",
            "src": "contracts/token/GIFT.sol:35"
          },
          {
            "label": "tierFourMax",
            "offset": 0,
            "slot": "217",
            "type": "t_uint256",
            "contract": "GIFT",
            "src": "contracts/token/GIFT.sol:36"
          }
        ],
        "types": {
          "t_address": {
            "label": "address",
            "numberOfBytes": "20"
          },
          "t_array(t_uint256)45_storage": {
            "label": "uint256[45]",
            "numberOfBytes": "1440"
          },
          "t_array(t_uint256)49_storage": {
            "label": "uint256[49]",
            "numberOfBytes": "1568"
          },
          "t_array(t_uint256)50_storage": {
            "label": "uint256[50]",
            "numberOfBytes": "1600"
          },
          "t_array(t_uint256)dyn_storage": {
            "label": "uint256[]",
            "numberOfBytes": "32"
          },
          "t_bool": {
            "label": "bool",
            "numberOfBytes": "1"
          },
          "t_mapping(t_address,t_bool)": {
            "label": "mapping(address => bool)",
            "numberOfBytes": "32"
          },
          "t_mapping(t_address,t_mapping(t_address,t_uint256))": {
            "label": "mapping(address => mapping(address => uint256))",
            "numberOfBytes": "32"
          },
          "t_mapping(t_address,t_struct(Snapshots)3043_storage)": {
            "label": "mapping(address => struct ERC20Snapshot.Snapshots)",
            "numberOfBytes": "32"
          },
          "t_mapping(t_address,t_uint256)": {
            "label": "mapping(address => uint256)",
            "numberOfBytes": "32"
          },
          "t_string_storage": {
            "label": "string",
            "numberOfBytes": "32"
          },
          "t_struct(Snapshots)3043_storage": {
            "label": "struct ERC20Snapshot.Snapshots",
            "members": [
              {
                "label": "ids",
                "type": "t_array(t_uint256)dyn_storage",
                "offset": 0,
                "slot": "0"
              },
              {
                "label": "values",
                "type": "t_array(t_uint256)dyn_storage",
                "offset": 0,
                "slot": "1"
              }
            ],
            "numberOfBytes": "64"
          },
          "t_uint256": {
            "label": "uint256",
            "numberOfBytes": "32"
          },
          "t_uint8": {
            "label": "uint8",
            "numberOfBytes": "1"
          }
        }
      }
    },
    "12f62c5bc8fb83f38cd17e8a80bff2f546de06e6459eeba65637e097d0ceb407": {
      "address": "0xb6200d6d60BB3a7f5858d248B4775dCAFe3fEeb7",
      "txHash": "0x8b05ccced0d9e0eec13d8455e48ac6a7bac55cc9c6cadd4daa2a2d1d3f19e58e",
      "layout": {
        "solcVersion": "0.8.19",
        "storage": [
          {
            "label": "_initialized",
            "offset": 0,
            "slot": "0",
            "type": "t_uint8",
            "contract": "Initializable",
            "src": "@openzeppelin/contracts-upgradeable/proxy/utils/Initializable.sol:63",
            "retypedFrom": "bool"
          },
          {
            "label": "_initializing",
            "offset": 1,
            "slot": "0",
            "type": "t_bool",
            "contract": "Initializable",
            "src": "@openzeppelin/contracts-upgradeable/proxy/utils/Initializable.sol:68"
          },
          {
            "label": "__gap",
            "offset": 0,
            "slot": "1",
            "type": "t_array(t_uint256)50_storage",
            "contract": "ContextUpgradeable",
            "src": "@openzeppelin/contracts-upgradeable/utils/ContextUpgradeable.sol:36"
          },
          {
            "label": "_owner",
            "offset": 0,
            "slot": "51",
            "type": "t_address",
            "contract": "OwnableUpgradeable",
            "src": "@openzeppelin/contracts-upgradeable/access/OwnableUpgradeable.sol:22"
          },
          {
            "label": "__gap",
            "offset": 0,
            "slot": "52",
            "type": "t_array(t_uint256)49_storage",
            "contract": "OwnableUpgradeable",
            "src": "@openzeppelin/contracts-upgradeable/access/OwnableUpgradeable.sol:94"
          },
          {
            "label": "signValidationWhitelist",
            "offset": 0,
            "slot": "101",
            "type": "t_mapping(t_address,t_bool)",
            "contract": "Access",
            "src": "contracts/Access.sol:9"
          },
          {
            "label": "tokenUsed",
            "offset": 0,
            "slot": "102",
            "type": "t_mapping(t_address,t_mapping(t_bytes32,t_bool))",
            "contract": "Access",
            "src": "contracts/Access.sol:10"
          },
          {
            "label": "sendManagers",
            "offset": 0,
            "slot": "103",
            "type": "t_mapping(t_address,t_bool)",
            "contract": "Access",
            "src": "contracts/Access.sol:11"
          }
        ],
        "types": {
          "t_address": {
            "label": "address",
            "numberOfBytes": "20"
          },
          "t_array(t_uint256)49_storage": {
            "label": "uint256[49]",
            "numberOfBytes": "1568"
          },
          "t_array(t_uint256)50_storage": {
            "label": "uint256[50]",
            "numberOfBytes": "1600"
          },
          "t_bool": {
            "label": "bool",
            "numberOfBytes": "1"
          },
          "t_bytes32": {
            "label": "bytes32",
            "numberOfBytes": "32"
          },
          "t_mapping(t_address,t_bool)": {
            "label": "mapping(address => bool)",
            "numberOfBytes": "32"
          },
          "t_mapping(t_address,t_mapping(t_bytes32,t_bool))": {
            "label": "mapping(address => mapping(bytes32 => bool))",
            "numberOfBytes": "32"
          },
          "t_mapping(t_bytes32,t_bool)": {
            "label": "mapping(bytes32 => bool)",
            "numberOfBytes": "32"
          },
          "t_uint256": {
            "label": "uint256",
            "numberOfBytes": "32"
          },
          "t_uint8": {
            "label": "uint8",
            "numberOfBytes": "1"
          }
        }
      }
    },
    "a2970a058675437ef4fc75b860f552a820c72cfdecc03825d348cd4e037ba8ab": {
      "address": "0xb0b8dfa52D66273835da2dcdb18d206379FE5474",
      "txHash": "0x4787f760596f2109c8da58eb5c41183d23d528248b4f3b6cf9af59ecf61f31b4",
      "layout": {
        "solcVersion": "0.8.19",
        "storage": [
          {
            "label": "_initialized",
            "offset": 0,
            "slot": "0",
            "type": "t_uint8",
            "contract": "Initializable",
            "src": "@openzeppelin/contracts-upgradeable/proxy/utils/Initializable.sol:63",
            "retypedFrom": "bool"
          },
          {
            "label": "_initializing",
            "offset": 1,
            "slot": "0",
            "type": "t_bool",
            "contract": "Initializable",
            "src": "@openzeppelin/contracts-upgradeable/proxy/utils/Initializable.sol:68"
          },
          {
            "label": "reserveFeed",
            "offset": 2,
            "slot": "0",
            "type": "t_contract(AggregatorV3Interface)45",
            "contract": "ReserveConsumerV3",
            "src": "contracts/por/ReserveConsumerV3.sol:9"
          }
        ],
        "types": {
          "t_bool": {
            "label": "bool",
            "numberOfBytes": "1"
          },
          "t_contract(AggregatorV3Interface)45": {
            "label": "contract AggregatorV3Interface",
            "numberOfBytes": "20"
          },
          "t_uint8": {
            "label": "uint8",
            "numberOfBytes": "1"
          }
        }
      }
    },
    "faaf4ee2d47cbd16e90821067b5a520ccd50bb77e8b86ae026bb9e746f060b11": {
      "address": "0xB11555B323367ADf8fA29BF8120Dd40CF9490692",
      "txHash": "0xc8c7cb1850f6983f188e957bce8e5d3d440e224877d18f396c05ceb82d33fd0b",
      "layout": {
        "solcVersion": "0.8.19",
        "storage": [
          {
            "label": "_initialized",
            "offset": 0,
            "slot": "0",
            "type": "t_uint8",
            "contract": "Initializable",
            "src": "@openzeppelin/contracts-upgradeable/proxy/utils/Initializable.sol:63",
            "retypedFrom": "bool"
          },
          {
            "label": "_initializing",
            "offset": 1,
            "slot": "0",
            "type": "t_bool",
            "contract": "Initializable",
            "src": "@openzeppelin/contracts-upgradeable/proxy/utils/Initializable.sol:68"
          },
          {
            "label": "__gap",
            "offset": 0,
            "slot": "1",
            "type": "t_array(t_uint256)50_storage",
            "contract": "ContextUpgradeable",
            "src": "@openzeppelin/contracts-upgradeable/utils/ContextUpgradeable.sol:36"
          },
          {
            "label": "_owner",
            "offset": 0,
            "slot": "51",
            "type": "t_address",
            "contract": "OwnableUpgradeable",
            "src": "@openzeppelin/contracts-upgradeable/access/OwnableUpgradeable.sol:22"
          },
          {
            "label": "__gap",
            "offset": 0,
            "slot": "52",
            "type": "t_array(t_uint256)49_storage",
            "contract": "OwnableUpgradeable",
            "src": "@openzeppelin/contracts-upgradeable/access/OwnableUpgradeable.sol:94"
          },
          {
            "label": "_balances",
            "offset": 0,
            "slot": "101",
            "type": "t_mapping(t_address,t_uint256)",
            "contract": "ERC20Upgradeable",
            "src": "@openzeppelin/contracts-upgradeable/token/ERC20/ERC20Upgradeable.sol:40"
          },
          {
            "label": "_allowances",
            "offset": 0,
            "slot": "102",
            "type": "t_mapping(t_address,t_mapping(t_address,t_uint256))",
            "contract": "ERC20Upgradeable",
            "src": "@openzeppelin/contracts-upgradeable/token/ERC20/ERC20Upgradeable.sol:42"
          },
          {
            "label": "_totalSupply",
            "offset": 0,
            "slot": "103",
            "type": "t_uint256",
            "contract": "ERC20Upgradeable",
            "src": "@openzeppelin/contracts-upgradeable/token/ERC20/ERC20Upgradeable.sol:44"
          },
          {
            "label": "_name",
            "offset": 0,
            "slot": "104",
            "type": "t_string_storage",
            "contract": "ERC20Upgradeable",
            "src": "@openzeppelin/contracts-upgradeable/token/ERC20/ERC20Upgradeable.sol:46"
          },
          {
            "label": "_symbol",
            "offset": 0,
            "slot": "105",
            "type": "t_string_storage",
            "contract": "ERC20Upgradeable",
            "src": "@openzeppelin/contracts-upgradeable/token/ERC20/ERC20Upgradeable.sol:47"
          },
          {
            "label": "__gap",
            "offset": 0,
            "slot": "106",
            "type": "t_array(t_uint256)45_storage",
            "contract": "ERC20Upgradeable",
            "src": "@openzeppelin/contracts-upgradeable/token/ERC20/ERC20Upgradeable.sol:376"
          },
          {
            "label": "_paused",
            "offset": 0,
            "slot": "151",
            "type": "t_bool",
            "contract": "PausableUpgradeable",
            "src": "@openzeppelin/contracts-upgradeable/security/PausableUpgradeable.sol:29"
          },
          {
            "label": "__gap",
            "offset": 0,
            "slot": "152",
            "type": "t_array(t_uint256)49_storage",
            "contract": "PausableUpgradeable",
            "src": "@openzeppelin/contracts-upgradeable/security/PausableUpgradeable.sol:116"
          },
          {
            "label": "_accountBalanceSnapshots",
            "offset": 0,
            "slot": "201",
            "type": "t_mapping(t_address,t_struct(Snapshots)3043_storage)",
            "contract": "ERC20Snapshot",
            "src": "contracts/ERC20Snapshot.sol:61"
          },
          {
            "label": "_totalSupplySnapshots",
            "offset": 0,
            "slot": "202",
            "type": "t_struct(Snapshots)3043_storage",
            "contract": "ERC20Snapshot",
            "src": "contracts/ERC20Snapshot.sol:62"
          },
          {
            "label": "_currentSnapshotId",
            "offset": 0,
            "slot": "204",
            "type": "t_uint256",
            "contract": "ERC20Snapshot",
            "src": "contracts/ERC20Snapshot.sol:65"
          },
          {
            "label": "supplyController",
            "offset": 0,
            "slot": "205",
            "type": "t_address",
            "contract": "GIFT",
            "src": "contracts/token/GIFT.sol:23"
          },
          {
            "label": "beneficiary",
            "offset": 0,
            "slot": "206",
            "type": "t_address",
            "contract": "GIFT",
            "src": "contracts/token/GIFT.sol:24"
          },
          {
            "label": "accessControl",
            "offset": 0,
            "slot": "207",
            "type": "t_address",
            "contract": "GIFT",
            "src": "contracts/token/GIFT.sol:26"
          },
          {
            "label": "reserveConsumer",
            "offset": 0,
            "slot": "208",
            "type": "t_address",
            "contract": "GIFT",
            "src": "contracts/token/GIFT.sol:27"
          },
          {
            "label": "_isExcludedFromFees",
            "offset": 0,
            "slot": "209",
            "type": "t_mapping(t_address,t_bool)",
            "contract": "GIFT",
            "src": "contracts/token/GIFT.sol:30"
          },
          {
            "label": "_isLiquidityPool",
            "offset": 0,
            "slot": "210",
            "type": "t_mapping(t_address,t_bool)",
            "contract": "GIFT",
            "src": "contracts/token/GIFT.sol:31"
          },
          {
            "label": "tierOneTaxPercentage",
            "offset": 0,
            "slot": "211",
            "type": "t_uint256",
            "contract": "GIFT",
            "src": "contracts/token/GIFT.sol:33"
          },
          {
            "label": "tierTwoTaxPercentage",
            "offset": 0,
            "slot": "212",
            "type": "t_uint256",
            "contract": "GIFT",
            "src": "contracts/token/GIFT.sol:34"
          },
          {
            "label": "tierThreeTaxPercentage",
            "offset": 0,
            "slot": "213",
            "type": "t_uint256",
            "contract": "GIFT",
            "src": "contracts/token/GIFT.sol:35"
          },
          {
            "label": "tierFourTaxPercentage",
            "offset": 0,
            "slot": "214",
            "type": "t_uint256",
            "contract": "GIFT",
            "src": "contracts/token/GIFT.sol:36"
          },
          {
            "label": "tierFiveTaxPercentage",
            "offset": 0,
            "slot": "215",
            "type": "t_uint256",
            "contract": "GIFT",
            "src": "contracts/token/GIFT.sol:37"
          },
          {
            "label": "tierOneMax",
            "offset": 0,
            "slot": "216",
            "type": "t_uint256",
            "contract": "GIFT",
            "src": "contracts/token/GIFT.sol:39"
          },
          {
            "label": "tierTwoMax",
            "offset": 0,
            "slot": "217",
            "type": "t_uint256",
            "contract": "GIFT",
            "src": "contracts/token/GIFT.sol:40"
          },
          {
            "label": "tierThreeMax",
            "offset": 0,
            "slot": "218",
            "type": "t_uint256",
            "contract": "GIFT",
            "src": "contracts/token/GIFT.sol:41"
          },
          {
            "label": "tierFourMax",
            "offset": 0,
            "slot": "219",
            "type": "t_uint256",
            "contract": "GIFT",
            "src": "contracts/token/GIFT.sol:42"
          }
        ],
        "types": {
          "t_address": {
            "label": "address",
            "numberOfBytes": "20"
          },
          "t_array(t_uint256)45_storage": {
            "label": "uint256[45]",
            "numberOfBytes": "1440"
          },
          "t_array(t_uint256)49_storage": {
            "label": "uint256[49]",
            "numberOfBytes": "1568"
          },
          "t_array(t_uint256)50_storage": {
            "label": "uint256[50]",
            "numberOfBytes": "1600"
          },
          "t_array(t_uint256)dyn_storage": {
            "label": "uint256[]",
            "numberOfBytes": "32"
          },
          "t_bool": {
            "label": "bool",
            "numberOfBytes": "1"
          },
          "t_mapping(t_address,t_bool)": {
            "label": "mapping(address => bool)",
            "numberOfBytes": "32"
          },
          "t_mapping(t_address,t_mapping(t_address,t_uint256))": {
            "label": "mapping(address => mapping(address => uint256))",
            "numberOfBytes": "32"
          },
          "t_mapping(t_address,t_struct(Snapshots)3043_storage)": {
            "label": "mapping(address => struct ERC20Snapshot.Snapshots)",
            "numberOfBytes": "32"
          },
          "t_mapping(t_address,t_uint256)": {
            "label": "mapping(address => uint256)",
            "numberOfBytes": "32"
          },
          "t_string_storage": {
            "label": "string",
            "numberOfBytes": "32"
          },
          "t_struct(Snapshots)3043_storage": {
            "label": "struct ERC20Snapshot.Snapshots",
            "members": [
              {
                "label": "ids",
                "type": "t_array(t_uint256)dyn_storage",
                "offset": 0,
                "slot": "0"
              },
              {
                "label": "values",
                "type": "t_array(t_uint256)dyn_storage",
                "offset": 0,
                "slot": "1"
              }
            ],
            "numberOfBytes": "64"
          },
          "t_uint256": {
            "label": "uint256",
            "numberOfBytes": "32"
          },
          "t_uint8": {
            "label": "uint8",
            "numberOfBytes": "1"
          }
        }
      }
    }
  }
}
